express/__init__.py
express/mixins.py
express/settings.py
express/parsers/__init__.py
express/parsers/crystal.py
express/parsers/molecule.py
express/parsers/settings.py
express/parsers/structure.py
express/parsers/utils.py
express/parsers/apps/__init__.py
express/parsers/apps/espresso/__init__.py
express/parsers/apps/espresso/parser.py
express/parsers/apps/espresso/settings.py
express/parsers/apps/espresso/formats/__init__.py
express/parsers/apps/espresso/formats/txt.py
express/parsers/apps/espresso/formats/xml/__init__.py
express/parsers/apps/espresso/formats/xml/xml_base.py
express/parsers/apps/espresso/formats/xml/xml_factory.py
express/parsers/apps/espresso/formats/xml/xml_post64.py
express/parsers/apps/nwchem/__init__.py
express/parsers/apps/nwchem/parser.py
express/parsers/apps/nwchem/settings.py
express/parsers/apps/nwchem/formats/__init__.py
express/parsers/apps/nwchem/formats/txt.py
express/parsers/apps/vasp/__init__.py
express/parsers/apps/vasp/parser.py
express/parsers/apps/vasp/settings.py
express/parsers/apps/vasp/formats/__init__.py
express/parsers/apps/vasp/formats/txt.py
express/parsers/apps/vasp/formats/xml.py
express/parsers/formats/__init__.py
express/parsers/formats/txt.py
express/parsers/formats/xml.py
express/parsers/mixins/__init__.py
express/parsers/mixins/electronic.py
express/parsers/mixins/ionic.py
express/parsers/mixins/reciprocal.py
express/properties/__init__.py
express/properties/material.py
express/properties/utils.py
express/properties/workflow.py
express/properties/convergence/__init__.py
express/properties/convergence/electronic.py
express/properties/convergence/ionic.py
express/properties/non_scalar/__init__.py
express/properties/non_scalar/atomic_constraints.py
express/properties/non_scalar/atomic_forces.py
express/properties/non_scalar/bandgaps.py
express/properties/non_scalar/dielectric_tensor.py
express/properties/non_scalar/file_content.py
express/properties/non_scalar/hubbard_u.py
express/properties/non_scalar/hubbard_v.py
express_py-2026.1.23.post0.dist-info/licenses/LICENSE.md
express_py-2026.1.23.post0.dist-info/METADATA
express_py-2026.1.23.post0.dist-info/WHEEL
express_py-2026.1.23.post0.dist-info/top_level.txt
express_py-2026.1.23.post0.dist-info/RECORD
