Metadata-Version: 2.4
Name: express-py
Version: 2026.1.23.post0
Summary: EXcellent PRoperty Extractor and Serializer.
Author-email: "Exabyte Inc." <info@mat3ra.com>
License: # LICENSE
Classifier: Programming Language :: Python
Classifier: Programming Language :: Python :: 3
Classifier: Development Status :: 3 - Alpha
Classifier: Topic :: Software Development
Requires-Python: >=3.10
License-File: LICENSE.md
Requires-Dist: munch==2.5.0
Requires-Dist: pymatgen>=2023.8.10
Requires-Dist: ase>=3.17.0
Requires-Dist: mat3ra-esse>=2026.1.23
Requires-Dist: jarvis-tools>=2023.12.12
Requires-Dist: numpy<2,>=1.24.4
Provides-Extra: extra
Requires-Dist: rdkit==2024.3.2; extra == "extra"
Provides-Extra: tests
Requires-Dist: coverage[toml]>=5.3; extra == "tests"
Requires-Dist: pyyaml; extra == "tests"
Provides-Extra: all
Requires-Dist: express-py[tests]; extra == "all"
Requires-Dist: express-py[extra]; extra == "all"
Dynamic: license-file
